{
  "field" : "polygon16",
  "symmetry" : "octahedral",
  "orientations" : [ [ 1.0, 0.0, 0.0, 0.0, 0.0, 1.0, 0.0, 0.0, 0.0, 0.0, 1.0, 0.0, 0.0, 0.0, 0.0, 1.0 ], [ 1.0, 0.0, 0.0, 0.0, 0.0, 0.0, 1.0, 0.0, 0.0, -1.0, 0.0, 0.0, 0.0, 0.0, 0.0, 1.0 ], [ 1.0, 0.0, 0.0, 0.0, 0.0, -1.0, 0.0, 0.0, 0.0, 0.0, -1.0, 0.0, 0.0, 0.0, 0.0, 1.0 ], [ 1.0, 0.0, 0.0, 0.0, 0.0, 0.0, -1.0, 0.0, 0.0, 1.0, 0.0, 0.0, 0.0, 0.0, 0.0, 1.0 ], [ 0.0, 1.0, 0.0, 0.0, 0.0, 0.0, 1.0, 0.0, 1.0, 0.0, 0.0, 0.0, 0.0, 0.0, 0.0, 1.0 ], [ 0.0, 1.0, 0.0, 0.0, 1.0, 0.0, 0.0, 0.0, 0.0, 0.0, -1.0, 0.0, 0.0, 0.0, 0.0, 1.0 ], [ 0.0, 1.0, 0.0, 0.0, 0.0, 0.0, -1.0, 0.0, -1.0, 0.0, 0.0, 0.0, 0.0, 0.0, 0.0, 1.0 ], [ 0.0, 1.0, 0.0, 0.0, -1.0, 0.0, 0.0, 0.0, 0.0, 0.0, 1.0, 0.0, 0.0, 0.0, 0.0, 1.0 ], [ 0.0, 0.0, 1.0, 0.0, 1.0, 0.0, 0.0, 0.0, 0.0, 1.0, 0.0, 0.0, 0.0, 0.0, 0.0, 1.0 ], [ 0.0, 0.0, 1.0, 0.0, 0.0, 1.0, 0.0, 0.0, -1.0, 0.0, 0.0, 0.0, 0.0, 0.0, 0.0, 1.0 ], [ 0.0, 0.0, 1.0, 0.0, -1.0, 0.0, 0.0, 0.0, 0.0, -1.0, 0.0, 0.0, 0.0, 0.0, 0.0, 1.0 ], [ 0.0, 0.0, 1.0, 0.0, 0.0, -1.0, 0.0, 0.0, 1.0, 0.0, 0.0, 0.0, 0.0, 0.0, 0.0, 1.0 ], [ -1.0, 0.0, 0.0, 0.0, 0.0, -1.0, 0.0, 0.0, 0.0, 0.0, 1.0, 0.0, 0.0, 0.0, 0.0, 1.0 ], [ -1.0, 0.0, 0.0, 0.0, 0.0, 0.0, 1.0, 0.0, 0.0, 1.0, 0.0, 0.0, 0.0, 0.0, 0.0, 1.0 ], [ -1.0, 0.0, 0.0, 0.0, 0.0, 1.0, 0.0, 0.0, 0.0, 0.0, -1.0, 0.0, 0.0, 0.0, 0.0, 1.0 ], [ -1.0, 0.0, 0.0, 0.0, 0.0, 0.0, -1.0, 0.0, 0.0, -1.0, 0.0, 0.0, 0.0, 0.0, 0.0, 1.0 ], [ 0.0, -1.0, 0.0, 0.0, 0.0, 0.0, -1.0, 0.0, 1.0, 0.0, 0.0, 0.0, 0.0, 0.0, 0.0, 1.0 ], [ 0.0, -1.0, 0.0, 0.0, 1.0, 0.0, 0.0, 0.0, 0.0, 0.0, 1.0, 0.0, 0.0, 0.0, 0.0, 1.0 ], [ 0.0, -1.0, 0.0, 0.0, 0.0, 0.0, 1.0, 0.0, -1.0, 0.0, 0.0, 0.0, 0.0, 0.0, 0.0, 1.0 ], [ 0.0, -1.0, 0.0, 0.0, -1.0, 0.0, 0.0, 0.0, 0.0, 0.0, -1.0, 0.0, 0.0, 0.0, 0.0, 1.0 ], [ 0.0, 0.0, -1.0, 0.0, -1.0, 0.0, 0.0, 0.0, 0.0, 1.0, 0.0, 0.0, 0.0, 0.0, 0.0, 1.0 ], [ 0.0, 0.0, -1.0, 0.0, 0.0, 1.0, 0.0, 0.0, 1.0, 0.0, 0.0, 0.0, 0.0, 0.0, 0.0, 1.0 ], [ 0.0, 0.0, -1.0, 0.0, 1.0, 0.0, 0.0, 0.0, 0.0, -1.0, 0.0, 0.0, 0.0, 0.0, 0.0, 1.0 ], [ 0.0, 0.0, -1.0, 0.0, 0.0, -1.0, 0.0, 0.0, -1.0, 0.0, 0.0, 0.0, 0.0, 0.0, 0.0, 1.0 ] ],
  "lights" : {
    "directionalLights" : [ {
      "direction" : {
        "x" : 1.0,
        "y" : -1.0,
        "z" : -1.0
      },
      "color" : "#EBEBE4"
    }, {
      "direction" : {
        "x" : -1.0,
        "y" : 0.0,
        "z" : 0.0
      },
      "color" : "#E4E4EB"
    }, {
      "direction" : {
        "x" : 0.0,
        "y" : 0.0,
        "z" : -1.0
      },
      "color" : "#1E1E1E"
    } ],
    "backgroundColor" : "#AFC8DC",
    "ambientColor" : "#292929"
  },
  "camera" : {
    "position" : {
      "x" : 118.66341,
      "y" : 11.154847,
      "z" : -15.316869
    },
    "width" : 54.075,
    "farClipDistance" : 240.33289,
    "lookAtPoint" : {
      "x" : 0.0,
      "y" : 0.0,
      "z" : 0.0
    },
    "fieldOfView" : 0.44262898,
    "perspective" : false,
    "viewDistance" : 120.16664,
    "nearClipDistance" : 0.30041674,
    "stereo" : false,
    "upDirection" : {
      "x" : -0.14688724,
      "y" : 0.835498,
      "z" : -0.52949685
    },
    "lookDirection" : {
      "x" : -0.9874904,
      "y" : -0.092828155,
      "z" : 0.12746356
    }
  },
  "embedding" : [ 1.0, 0.0, 0.0, 0.0, 0.0, 1.0, 0.0, 0.0, 0.0, 0.0, 1.0, 0.0, 0.0, 0.0, 0.0, 1.0 ],
  "shapes" : [ {
    "id" : "f4712e3d-12dc-496e-a379-c20241718910",
    "vertices" : [ {
      "x" : 0.5197831,
      "y" : 0.0,
      "z" : 0.0
    }, {
      "x" : -0.5197831,
      "y" : 0.0,
      "z" : 0.0
    }, {
      "x" : 0.0,
      "y" : 0.5197831,
      "z" : 0.0
    }, {
      "x" : 0.0,
      "y" : -0.5197831,
      "z" : 0.0
    }, {
      "x" : 0.0,
      "y" : 0.0,
      "z" : 0.5197831
    }, {
      "x" : 0.0,
      "y" : 0.0,
      "z" : -0.5197831
    } ],
    "faces" : [ {
      "vertices" : [ 0, 2, 4 ]
    }, {
      "vertices" : [ 0, 5, 2 ]
    }, {
      "vertices" : [ 0, 4, 3 ]
    }, {
      "vertices" : [ 1, 4, 2 ]
    }, {
      "vertices" : [ 0, 3, 5 ]
    }, {
      "vertices" : [ 1, 2, 5 ]
    }, {
      "vertices" : [ 1, 3, 4 ]
    }, {
      "vertices" : [ 1, 5, 3 ]
    } ]
  }, {
    "id" : "f81faff3-7325-45d0-887d-14405df2c251",
    "vertices" : [ {
      "x" : -9.110821,
      "y" : 3.7738254,
      "z" : 3.7738254
    }, {
      "x" : -3.7738254,
      "y" : 3.7738254,
      "z" : 9.110821
    }, {
      "x" : -3.7738254,
      "y" : 9.110821,
      "z" : 3.7738254
    } ],
    "faces" : [ {
      "vertices" : [ 0, 1, 2 ]
    }, {
      "vertices" : [ 0, 2, 1 ]
    } ]
  }, {
    "id" : "33124546-fc37-463c-83d4-609c2b64436c",
    "vertices" : [ {
      "x" : 3.7738254,
      "y" : 3.7738254,
      "z" : -9.110821
    }, {
      "x" : 3.7738254,
      "y" : -3.7738254,
      "z" : -9.110821
    }, {
      "x" : -3.7738254,
      "y" : -3.7738254,
      "z" : -9.110821
    }, {
      "x" : -3.7738254,
      "y" : 3.7738254,
      "z" : -9.110821
    } ],
    "faces" : [ {
      "vertices" : [ 0, 1, 2 ]
    }, {
      "vertices" : [ 0, 2, 3 ]
    }, {
      "vertices" : [ 0, 3, 2 ]
    }, {
      "vertices" : [ 0, 2, 1 ]
    } ]
  }, {
    "id" : "205537e0-8581-4ba9-8720-98b31e1a3437",
    "vertices" : [ {
      "x" : 6.9143176,
      "y" : -0.1,
      "z" : -0.26666668
    }, {
      "x" : 6.8143177,
      "y" : -0.2,
      "z" : 0.13333334
    }, {
      "x" : 0.6333333,
      "y" : 0.1,
      "z" : 0.26666668
    }, {
      "x" : 0.73333335,
      "y" : 0.2,
      "z" : -0.13333334
    }, {
      "x" : 6.580984,
      "y" : 0.1,
      "z" : 0.26666668
    }, {
      "x" : 6.680984,
      "y" : 0.2,
      "z" : -0.13333334
    }, {
      "x" : 0.96666664,
      "y" : -0.1,
      "z" : -0.26666668
    }, {
      "x" : 0.8666667,
      "y" : -0.2,
      "z" : 0.13333334
    } ],
    "faces" : [ {
      "vertices" : [ 2, 3, 6 ]
    }, {
      "vertices" : [ 2, 6, 7 ]
    }, {
      "vertices" : [ 0, 5, 4 ]
    }, {
      "vertices" : [ 0, 4, 1 ]
    }, {
      "vertices" : [ 2, 4, 5 ]
    }, {
      "vertices" : [ 2, 5, 3 ]
    }, {
      "vertices" : [ 0, 6, 3 ]
    }, {
      "vertices" : [ 0, 3, 5 ]
    }, {
      "vertices" : [ 0, 1, 7 ]
    }, {
      "vertices" : [ 0, 7, 6 ]
    }, {
      "vertices" : [ 1, 4, 2 ]
    }, {
      "vertices" : [ 1, 2, 7 ]
    } ]
  }, {
    "id" : "d2fbd12e-e9af-404d-8b9f-e73f4cb6be72",
    "vertices" : [ {
      "x" : 4.9036617,
      "y" : 0.13333334,
      "z" : 4.6369953
    }, {
      "x" : 5.0036616,
      "y" : -0.26666668,
      "z" : 4.736995
    }, {
      "x" : 0.43333334,
      "y" : -0.13333334,
      "z" : 0.7
    }, {
      "x" : 0.33333334,
      "y" : 0.26666668,
      "z" : 0.6
    }, {
      "x" : 4.7703285,
      "y" : -0.13333334,
      "z" : 5.036995
    }, {
      "x" : 4.6703286,
      "y" : 0.26666668,
      "z" : 4.936995
    }, {
      "x" : 0.56666666,
      "y" : 0.13333334,
      "z" : 0.3
    }, {
      "x" : 0.6666667,
      "y" : -0.26666668,
      "z" : 0.4
    } ],
    "faces" : [ {
      "vertices" : [ 2, 3, 6 ]
    }, {
      "vertices" : [ 2, 6, 7 ]
    }, {
      "vertices" : [ 0, 5, 4 ]
    }, {
      "vertices" : [ 0, 4, 1 ]
    }, {
      "vertices" : [ 2, 4, 5 ]
    }, {
      "vertices" : [ 2, 5, 3 ]
    }, {
      "vertices" : [ 0, 6, 3 ]
    }, {
      "vertices" : [ 0, 3, 5 ]
    }, {
      "vertices" : [ 0, 1, 7 ]
    }, {
      "vertices" : [ 0, 7, 6 ]
    }, {
      "vertices" : [ 1, 4, 2 ]
    }, {
      "vertices" : [ 1, 2, 7 ]
    } ]
  }, {
    "id" : "d1408f2b-9635-45f4-bd5d-76dad3a3a256",
    "vertices" : [ {
      "x" : 9.110821,
      "y" : -3.7738254,
      "z" : -3.7738254
    }, {
      "x" : 9.110821,
      "y" : 3.7738254,
      "z" : -3.7738254
    }, {
      "x" : 9.110821,
      "y" : 3.7738254,
      "z" : 3.7738254
    }, {
      "x" : 9.110821,
      "y" : -3.7738254,
      "z" : 3.7738254
    } ],
    "faces" : [ {
      "vertices" : [ 0, 1, 2 ]
    }, {
      "vertices" : [ 0, 2, 3 ]
    }, {
      "vertices" : [ 0, 3, 2 ]
    }, {
      "vertices" : [ 0, 2, 1 ]
    } ]
  }, {
    "id" : "2a85f4c7-2893-4413-9eb8-2d04abcf95a2",
    "vertices" : [ {
      "x" : -3.7738254,
      "y" : 9.110821,
      "z" : -3.7738254
    }, {
      "x" : -3.7738254,
      "y" : 3.7738254,
      "z" : -9.110821
    }, {
      "x" : -9.110821,
      "y" : 3.7738254,
      "z" : -3.7738254
    } ],
    "faces" : [ {
      "vertices" : [ 0, 1, 2 ]
    }, {
      "vertices" : [ 0, 2, 1 ]
    } ]
  }, {
    "id" : "a5067b75-d4e0-457d-8676-9ddbd1a5df4f",
    "vertices" : [ {
      "x" : 3.7738254,
      "y" : 3.7738254,
      "z" : -9.110821
    }, {
      "x" : -3.7738254,
      "y" : 3.7738254,
      "z" : -9.110821
    }, {
      "x" : -3.7738254,
      "y" : 9.110821,
      "z" : -3.7738254
    }, {
      "x" : 3.7738254,
      "y" : 9.110821,
      "z" : -3.7738254
    } ],
    "faces" : [ {
      "vertices" : [ 0, 1, 2 ]
    }, {
      "vertices" : [ 0, 2, 3 ]
    }, {
      "vertices" : [ 0, 3, 2 ]
    }, {
      "vertices" : [ 0, 2, 1 ]
    } ]
  }, {
    "id" : "29154478-dd45-4da4-bab1-ec9305bca305",
    "vertices" : [ {
      "x" : 3.7738254,
      "y" : 3.7738254,
      "z" : 9.110821
    }, {
      "x" : 3.7738254,
      "y" : 9.110821,
      "z" : 3.7738254
    }, {
      "x" : -3.7738254,
      "y" : 9.110821,
      "z" : 3.7738254
    }, {
      "x" : -3.7738254,
      "y" : 3.7738254,
      "z" : 9.110821
    } ],
    "faces" : [ {
      "vertices" : [ 0, 1, 2 ]
    }, {
      "vertices" : [ 0, 2, 3 ]
    }, {
      "vertices" : [ 0, 3, 2 ]
    }, {
      "vertices" : [ 0, 2, 1 ]
    } ]
  }, {
    "id" : "f67f758c-6c3e-431d-8b39-b915fe4bf467",
    "vertices" : [ {
      "x" : 9.110821,
      "y" : -3.7738254,
      "z" : -3.7738254
    }, {
      "x" : 3.7738254,
      "y" : -9.110821,
      "z" : -3.7738254
    }, {
      "x" : 3.7738254,
      "y" : -3.7738254,
      "z" : -9.110821
    } ],
    "faces" : [ {
      "vertices" : [ 0, 1, 2 ]
    }, {
      "vertices" : [ 0, 2, 1 ]
    } ]
  }, {
    "id" : "6da46770-8560-4386-93b5-0857fb4977bc",
    "vertices" : [ {
      "x" : -3.7738254,
      "y" : -9.110821,
      "z" : 3.7738254
    }, {
      "x" : 3.7738254,
      "y" : -9.110821,
      "z" : 3.7738254
    }, {
      "x" : 3.7738254,
      "y" : -3.7738254,
      "z" : 9.110821
    }, {
      "x" : -3.7738254,
      "y" : -3.7738254,
      "z" : 9.110821
    } ],
    "faces" : [ {
      "vertices" : [ 0, 1, 2 ]
    }, {
      "vertices" : [ 0, 2, 3 ]
    }, {
      "vertices" : [ 0, 3, 2 ]
    }, {
      "vertices" : [ 0, 2, 1 ]
    } ]
  }, {
    "id" : "9418330a-e9b1-4b74-b119-70db2e54bc35",
    "vertices" : [ {
      "x" : 3.7738254,
      "y" : -9.110821,
      "z" : 3.7738254
    }, {
      "x" : 9.110821,
      "y" : -3.7738254,
      "z" : 3.7738254
    }, {
      "x" : 3.7738254,
      "y" : -3.7738254,
      "z" : 9.110821
    } ],
    "faces" : [ {
      "vertices" : [ 0, 1, 2 ]
    }, {
      "vertices" : [ 0, 2, 1 ]
    } ]
  }, {
    "id" : "8b79418b-5839-4001-8d52-0a279373b998",
    "vertices" : [ {
      "x" : -3.7738254,
      "y" : -3.7738254,
      "z" : -9.110821
    }, {
      "x" : -9.110821,
      "y" : -3.7738254,
      "z" : -3.7738254
    }, {
      "x" : -9.110821,
      "y" : 3.7738254,
      "z" : -3.7738254
    }, {
      "x" : -3.7738254,
      "y" : 3.7738254,
      "z" : -9.110821
    } ],
    "faces" : [ {
      "vertices" : [ 0, 1, 2 ]
    }, {
      "vertices" : [ 0, 2, 3 ]
    }, {
      "vertices" : [ 0, 3, 2 ]
    }, {
      "vertices" : [ 0, 2, 1 ]
    } ]
  }, {
    "id" : "bf7ff0f0-6070-4a43-a76a-ed960a84a589",
    "vertices" : [ {
      "x" : -9.110821,
      "y" : 3.7738254,
      "z" : 3.7738254
    }, {
      "x" : -9.110821,
      "y" : 3.7738254,
      "z" : -3.7738254
    }, {
      "x" : -9.110821,
      "y" : -3.7738254,
      "z" : -3.7738254
    }, {
      "x" : -9.110821,
      "y" : -3.7738254,
      "z" : 3.7738254
    } ],
    "faces" : [ {
      "vertices" : [ 0, 1, 2 ]
    }, {
      "vertices" : [ 0, 2, 3 ]
    }, {
      "vertices" : [ 0, 3, 2 ]
    }, {
      "vertices" : [ 0, 2, 1 ]
    } ]
  }, {
    "id" : "229a382c-f152-44c2-9d4a-457eeb9c359f",
    "vertices" : [ {
      "x" : -3.7738254,
      "y" : -3.7738254,
      "z" : -9.110821
    }, {
      "x" : -3.7738254,
      "y" : -9.110821,
      "z" : -3.7738254
    }, {
      "x" : -9.110821,
      "y" : -3.7738254,
      "z" : -3.7738254
    } ],
    "faces" : [ {
      "vertices" : [ 0, 1, 2 ]
    }, {
      "vertices" : [ 0, 2, 1 ]
    } ]
  }, {
    "id" : "8cb92359-f916-4136-9ffa-70d9d2bc412d",
    "vertices" : [ {
      "x" : 3.7738254,
      "y" : 3.7738254,
      "z" : 9.110821
    }, {
      "x" : 9.110821,
      "y" : 3.7738254,
      "z" : 3.7738254
    }, {
      "x" : 3.7738254,
      "y" : 9.110821,
      "z" : 3.7738254
    } ],
    "faces" : [ {
      "vertices" : [ 0, 1, 2 ]
    }, {
      "vertices" : [ 0, 2, 1 ]
    } ]
  }, {
    "id" : "2cdc8995-46fa-4209-add9-63df74495d35",
    "vertices" : [ {
      "x" : -3.7738254,
      "y" : -9.110821,
      "z" : 3.7738254
    }, {
      "x" : -3.7738254,
      "y" : -9.110821,
      "z" : -3.7738254
    }, {
      "x" : 3.7738254,
      "y" : -9.110821,
      "z" : -3.7738254
    }, {
      "x" : 3.7738254,
      "y" : -9.110821,
      "z" : 3.7738254
    } ],
    "faces" : [ {
      "vertices" : [ 0, 1, 2 ]
    }, {
      "vertices" : [ 0, 2, 3 ]
    }, {
      "vertices" : [ 0, 3, 2 ]
    }, {
      "vertices" : [ 0, 2, 1 ]
    } ]
  }, {
    "id" : "572f9828-b639-4e7f-bf40-b08882ab212a",
    "vertices" : [ {
      "x" : 3.7738254,
      "y" : 3.7738254,
      "z" : 9.110821
    }, {
      "x" : -3.7738254,
      "y" : 3.7738254,
      "z" : 9.110821
    }, {
      "x" : -3.7738254,
      "y" : -3.7738254,
      "z" : 9.110821
    }, {
      "x" : 3.7738254,
      "y" : -3.7738254,
      "z" : 9.110821
    } ],
    "faces" : [ {
      "vertices" : [ 0, 1, 2 ]
    }, {
      "vertices" : [ 0, 2, 3 ]
    }, {
      "vertices" : [ 0, 3, 2 ]
    }, {
      "vertices" : [ 0, 2, 1 ]
    } ]
  }, {
    "id" : "9c939a3a-4855-49cb-9351-dbff5f00c3fd",
    "vertices" : [ {
      "x" : 3.7738254,
      "y" : 9.110821,
      "z" : -3.7738254
    }, {
      "x" : 3.7738254,
      "y" : 9.110821,
      "z" : 3.7738254
    }, {
      "x" : 9.110821,
      "y" : 3.7738254,
      "z" : 3.7738254
    }, {
      "x" : 9.110821,
      "y" : 3.7738254,
      "z" : -3.7738254
    } ],
    "faces" : [ {
      "vertices" : [ 0, 1, 2 ]
    }, {
      "vertices" : [ 0, 2, 3 ]
    }, {
      "vertices" : [ 0, 3, 2 ]
    }, {
      "vertices" : [ 0, 2, 1 ]
    } ]
  }, {
    "id" : "683a5a6e-6f98-4664-b0ac-026f7e123186",
    "vertices" : [ {
      "x" : -3.7738254,
      "y" : -3.7738254,
      "z" : 9.110821
    }, {
      "x" : -3.7738254,
      "y" : 3.7738254,
      "z" : 9.110821
    }, {
      "x" : -9.110821,
      "y" : 3.7738254,
      "z" : 3.7738254
    }, {
      "x" : -9.110821,
      "y" : -3.7738254,
      "z" : 3.7738254
    } ],
    "faces" : [ {
      "vertices" : [ 0, 1, 2 ]
    }, {
      "vertices" : [ 0, 2, 3 ]
    }, {
      "vertices" : [ 0, 3, 2 ]
    }, {
      "vertices" : [ 0, 2, 1 ]
    } ]
  }, {
    "id" : "b1594420-ad93-4673-934e-bfad2cac7f8d",
    "vertices" : [ {
      "x" : 3.7738254,
      "y" : 3.7738254,
      "z" : 9.110821
    }, {
      "x" : 3.7738254,
      "y" : -3.7738254,
      "z" : 9.110821
    }, {
      "x" : 9.110821,
      "y" : -3.7738254,
      "z" : 3.7738254
    }, {
      "x" : 9.110821,
      "y" : 3.7738254,
      "z" : 3.7738254
    } ],
    "faces" : [ {
      "vertices" : [ 0, 1, 2 ]
    }, {
      "vertices" : [ 0, 2, 3 ]
    }, {
      "vertices" : [ 0, 3, 2 ]
    }, {
      "vertices" : [ 0, 2, 1 ]
    } ]
  }, {
    "id" : "dce7d9c2-016f-4be0-b60c-22aa2b370c85",
    "vertices" : [ {
      "x" : 3.7738254,
      "y" : 3.7738254,
      "z" : -9.110821
    }, {
      "x" : 3.7738254,
      "y" : 9.110821,
      "z" : -3.7738254
    }, {
      "x" : 9.110821,
      "y" : 3.7738254,
      "z" : -3.7738254
    } ],
    "faces" : [ {
      "vertices" : [ 0, 1, 2 ]
    }, {
      "vertices" : [ 0, 2, 1 ]
    } ]
  }, {
    "id" : "6084b1d5-613c-4800-9f40-f45dbb535e01",
    "vertices" : [ {
      "x" : -3.7738254,
      "y" : 9.110821,
      "z" : -3.7738254
    }, {
      "x" : -3.7738254,
      "y" : 9.110821,
      "z" : 3.7738254
    }, {
      "x" : 3.7738254,
      "y" : 9.110821,
      "z" : 3.7738254
    }, {
      "x" : 3.7738254,
      "y" : 9.110821,
      "z" : -3.7738254
    } ],
    "faces" : [ {
      "vertices" : [ 0, 1, 2 ]
    }, {
      "vertices" : [ 0, 2, 3 ]
    }, {
      "vertices" : [ 0, 3, 2 ]
    }, {
      "vertices" : [ 0, 2, 1 ]
    } ]
  }, {
    "id" : "d5bb01bd-8a83-44d9-8994-15159489fcd6",
    "vertices" : [ {
      "x" : -3.7738254,
      "y" : -9.110821,
      "z" : 3.7738254
    }, {
      "x" : -3.7738254,
      "y" : -3.7738254,
      "z" : 9.110821
    }, {
      "x" : -9.110821,
      "y" : -3.7738254,
      "z" : 3.7738254
    } ],
    "faces" : [ {
      "vertices" : [ 0, 1, 2 ]
    }, {
      "vertices" : [ 0, 2, 1 ]
    } ]
  }, {
    "id" : "833c05aa-cb0e-4b58-a49e-612b9cb22153",
    "vertices" : [ {
      "x" : -3.7738254,
      "y" : -9.110821,
      "z" : 3.7738254
    }, {
      "x" : -9.110821,
      "y" : -3.7738254,
      "z" : 3.7738254
    }, {
      "x" : -9.110821,
      "y" : -3.7738254,
      "z" : -3.7738254
    }, {
      "x" : -3.7738254,
      "y" : -9.110821,
      "z" : -3.7738254
    } ],
    "faces" : [ {
      "vertices" : [ 0, 1, 2 ]
    }, {
      "vertices" : [ 0, 2, 3 ]
    }, {
      "vertices" : [ 0, 3, 2 ]
    }, {
      "vertices" : [ 0, 2, 1 ]
    } ]
  }, {
    "id" : "985dd9d6-9c4b-4e32-94f2-259c34228aab",
    "vertices" : [ {
      "x" : -3.7738254,
      "y" : 9.110821,
      "z" : -3.7738254
    }, {
      "x" : -9.110821,
      "y" : 3.7738254,
      "z" : -3.7738254
    }, {
      "x" : -9.110821,
      "y" : 3.7738254,
      "z" : 3.7738254
    }, {
      "x" : -3.7738254,
      "y" : 9.110821,
      "z" : 3.7738254
    } ],
    "faces" : [ {
      "vertices" : [ 0, 1, 2 ]
    }, {
      "vertices" : [ 0, 2, 3 ]
    }, {
      "vertices" : [ 0, 3, 2 ]
    }, {
      "vertices" : [ 0, 2, 1 ]
    } ]
  }, {
    "id" : "5bd03eeb-c3ff-49fa-ab0f-2d7a2304d3fd",
    "vertices" : [ {
      "x" : 3.7738254,
      "y" : 3.7738254,
      "z" : -9.110821
    }, {
      "x" : 9.110821,
      "y" : 3.7738254,
      "z" : -3.7738254
    }, {
      "x" : 9.110821,
      "y" : -3.7738254,
      "z" : -3.7738254
    }, {
      "x" : 3.7738254,
      "y" : -3.7738254,
      "z" : -9.110821
    } ],
    "faces" : [ {
      "vertices" : [ 0, 1, 2 ]
    }, {
      "vertices" : [ 0, 2, 3 ]
    }, {
      "vertices" : [ 0, 3, 2 ]
    }, {
      "vertices" : [ 0, 2, 1 ]
    } ]
  }, {
    "id" : "7a58878c-e75c-4c99-b48a-556928cc13db",
    "vertices" : [ {
      "x" : -3.7738254,
      "y" : -3.7738254,
      "z" : -9.110821
    }, {
      "x" : 3.7738254,
      "y" : -3.7738254,
      "z" : -9.110821
    }, {
      "x" : 3.7738254,
      "y" : -9.110821,
      "z" : -3.7738254
    }, {
      "x" : -3.7738254,
      "y" : -9.110821,
      "z" : -3.7738254
    } ],
    "faces" : [ {
      "vertices" : [ 0, 1, 2 ]
    }, {
      "vertices" : [ 0, 2, 3 ]
    }, {
      "vertices" : [ 0, 3, 2 ]
    }, {
      "vertices" : [ 0, 2, 1 ]
    } ]
  }, {
    "id" : "68352985-3a73-43cd-b686-f3598374c5e9",
    "vertices" : [ {
      "x" : 9.110821,
      "y" : -3.7738254,
      "z" : -3.7738254
    }, {
      "x" : 9.110821,
      "y" : -3.7738254,
      "z" : 3.7738254
    }, {
      "x" : 3.7738254,
      "y" : -9.110821,
      "z" : 3.7738254
    }, {
      "x" : 3.7738254,
      "y" : -9.110821,
      "z" : -3.7738254
    } ],
    "faces" : [ {
      "vertices" : [ 0, 1, 2 ]
    }, {
      "vertices" : [ 0, 2, 3 ]
    }, {
      "vertices" : [ 0, 3, 2 ]
    }, {
      "vertices" : [ 0, 2, 1 ]
    } ]
  } ],
  "instances" : [ {
    "shape" : "f4712e3d-12dc-496e-a379-c20241718910",
    "color" : "#000000",
    "position" : {
      "x" : -9.110821,
      "y" : -3.7738254,
      "z" : 3.7738254
    }
  }, {
    "shape" : "f81faff3-7325-45d0-887d-14405df2c251",
    "color" : "#0000FF",
    "position" : {
      "x" : 0.0,
      "y" : 0.0,
      "z" : 0.0
    }
  }, {
    "shape" : "f4712e3d-12dc-496e-a379-c20241718910",
    "color" : "#000000",
    "position" : {
      "x" : -3.7738254,
      "y" : -9.110821,
      "z" : 3.7738254
    }
  }, {
    "shape" : "33124546-fc37-463c-83d4-609c2b64436c",
    "color" : "#FFFFFF",
    "position" : {
      "x" : 0.0,
      "y" : 0.0,
      "z" : 0.0
    }
  }, {
    "shape" : "205537e0-8581-4ba9-8720-98b31e1a3437",
    "color" : "#000000",
    "position" : {
      "x" : -3.7738254,
      "y" : 3.7738254,
      "z" : 9.110821
    },
    "orientation" : 7
  }, {
    "shape" : "d2fbd12e-e9af-404d-8b9f-e73f4cb6be72",
    "color" : "#000000",
    "position" : {
      "x" : 3.7738254,
      "y" : -3.7738254,
      "z" : 9.110821
    },
    "orientation" : 19
  }, {
    "shape" : "f4712e3d-12dc-496e-a379-c20241718910",
    "color" : "#000000",
    "position" : {
      "x" : 3.7738254,
      "y" : 9.110821,
      "z" : 3.7738254
    }
  }, {
    "shape" : "d1408f2b-9635-45f4-bd5d-76dad3a3a256",
    "color" : "#FFFFFF",
    "position" : {
      "x" : 0.0,
      "y" : 0.0,
      "z" : 0.0
    }
  }, {
    "shape" : "2a85f4c7-2893-4413-9eb8-2d04abcf95a2",
    "color" : "#0000FF",
    "position" : {
      "x" : 0.0,
      "y" : 0.0,
      "z" : 0.0
    }
  }, {
    "shape" : "f4712e3d-12dc-496e-a379-c20241718910",
    "color" : "#000000",
    "position" : {
      "x" : 3.7738254,
      "y" : 3.7738254,
      "z" : -9.110821
    }
  }, {
    "shape" : "d2fbd12e-e9af-404d-8b9f-e73f4cb6be72",
    "color" : "#000000",
    "position" : {
      "x" : 3.7738254,
      "y" : 3.7738254,
      "z" : 9.110821
    },
    "orientation" : 18
  }, {
    "shape" : "f4712e3d-12dc-496e-a379-c20241718910",
    "color" : "#000000",
    "position" : {
      "x" : -3.7738254,
      "y" : 3.7738254,
      "z" : 9.110821
    }
  }, {
    "shape" : "205537e0-8581-4ba9-8720-98b31e1a3437",
    "color" : "#000000",
    "position" : {
      "x" : 3.7738254,
      "y" : -3.7738254,
      "z" : -9.110821
    },
    "orientation" : 12
  }, {
    "shape" : "205537e0-8581-4ba9-8720-98b31e1a3437",
    "color" : "#000000",
    "position" : {
      "x" : 3.7738254,
      "y" : 3.7738254,
      "z" : -9.110821
    },
    "orientation" : 12
  }, {
    "shape" : "f4712e3d-12dc-496e-a379-c20241718910",
    "color" : "#000000",
    "position" : {
      "x" : 3.7738254,
      "y" : -3.7738254,
      "z" : 9.110821
    }
  }, {
    "shape" : "205537e0-8581-4ba9-8720-98b31e1a3437",
    "color" : "#000000",
    "position" : {
      "x" : 3.7738254,
      "y" : 3.7738254,
      "z" : 9.110821
    },
    "orientation" : 7
  }, {
    "shape" : "f4712e3d-12dc-496e-a379-c20241718910",
    "color" : "#000000",
    "position" : {
      "x" : 3.7738254,
      "y" : -3.7738254,
      "z" : -9.110821
    }
  }, {
    "shape" : "a5067b75-d4e0-457d-8676-9ddbd1a5df4f",
    "color" : "#FFFFFF",
    "position" : {
      "x" : 0.0,
      "y" : 0.0,
      "z" : 0.0
    }
  }, {
    "shape" : "f4712e3d-12dc-496e-a379-c20241718910",
    "color" : "#000000",
    "position" : {
      "x" : -3.7738254,
      "y" : 9.110821,
      "z" : -3.7738254
    }
  }, {
    "shape" : "205537e0-8581-4ba9-8720-98b31e1a3437",
    "color" : "#000000",
    "position" : {
      "x" : 9.110821,
      "y" : 3.7738254,
      "z" : -3.7738254
    },
    "orientation" : 4
  }, {
    "shape" : "f4712e3d-12dc-496e-a379-c20241718910",
    "color" : "#000000",
    "position" : {
      "x" : -3.7738254,
      "y" : -3.7738254,
      "z" : 9.110821
    }
  }, {
    "shape" : "d2fbd12e-e9af-404d-8b9f-e73f4cb6be72",
    "color" : "#000000",
    "position" : {
      "x" : -3.7738254,
      "y" : 3.7738254,
      "z" : -9.110821
    },
    "orientation" : 12
  }, {
    "shape" : "d2fbd12e-e9af-404d-8b9f-e73f4cb6be72",
    "color" : "#000000",
    "position" : {
      "x" : -9.110821,
      "y" : 3.7738254,
      "z" : 3.7738254
    },
    "orientation" : 1
  }, {
    "shape" : "205537e0-8581-4ba9-8720-98b31e1a3437",
    "color" : "#000000",
    "position" : {
      "x" : -3.7738254,
      "y" : 3.7738254,
      "z" : 9.110821
    },
    "orientation" : 0
  }, {
    "shape" : "29154478-dd45-4da4-bab1-ec9305bca305",
    "color" : "#FFFFFF",
    "position" : {
      "x" : 0.0,
      "y" : 0.0,
      "z" : 0.0
    }
  }, {
    "shape" : "f4712e3d-12dc-496e-a379-c20241718910",
    "color" : "#000000",
    "position" : {
      "x" : -3.7738254,
      "y" : 3.7738254,
      "z" : -9.110821
    }
  }, {
    "shape" : "d2fbd12e-e9af-404d-8b9f-e73f4cb6be72",
    "color" : "#000000",
    "position" : {
      "x" : 3.7738254,
      "y" : -9.110821,
      "z" : 3.7738254
    },
    "orientation" : 1
  }, {
    "shape" : "205537e0-8581-4ba9-8720-98b31e1a3437",
    "color" : "#000000",
    "position" : {
      "x" : 3.7738254,
      "y" : -9.110821,
      "z" : -3.7738254
    },
    "orientation" : 12
  }, {
    "shape" : "205537e0-8581-4ba9-8720-98b31e1a3437",
    "color" : "#000000",
    "position" : {
      "x" : 3.7738254,
      "y" : -9.110821,
      "z" : 3.7738254
    },
    "orientation" : 12
  }, {
    "shape" : "f67f758c-6c3e-431d-8b39-b915fe4bf467",
    "color" : "#0000FF",
    "position" : {
      "x" : 0.0,
      "y" : 0.0,
      "z" : 0.0
    }
  }, {
    "shape" : "d2fbd12e-e9af-404d-8b9f-e73f4cb6be72",
    "color" : "#000000",
    "position" : {
      "x" : 3.7738254,
      "y" : -9.110821,
      "z" : -3.7738254
    },
    "orientation" : 1
  }, {
    "shape" : "f4712e3d-12dc-496e-a379-c20241718910",
    "color" : "#000000",
    "position" : {
      "x" : 9.110821,
      "y" : 3.7738254,
      "z" : -3.7738254
    }
  }, {
    "shape" : "f4712e3d-12dc-496e-a379-c20241718910",
    "color" : "#000000",
    "position" : {
      "x" : -9.110821,
      "y" : 3.7738254,
      "z" : -3.7738254
    }
  }, {
    "shape" : "d2fbd12e-e9af-404d-8b9f-e73f4cb6be72",
    "color" : "#000000",
    "position" : {
      "x" : -9.110821,
      "y" : -3.7738254,
      "z" : -3.7738254
    },
    "orientation" : 2
  }, {
    "shape" : "f4712e3d-12dc-496e-a379-c20241718910",
    "color" : "#000000",
    "position" : {
      "x" : 9.110821,
      "y" : -3.7738254,
      "z" : -3.7738254
    }
  }, {
    "shape" : "f4712e3d-12dc-496e-a379-c20241718910",
    "color" : "#000000",
    "position" : {
      "x" : 3.7738254,
      "y" : -9.110821,
      "z" : 3.7738254
    }
  }, {
    "shape" : "d2fbd12e-e9af-404d-8b9f-e73f4cb6be72",
    "color" : "#000000",
    "position" : {
      "x" : -3.7738254,
      "y" : -3.7738254,
      "z" : 9.110821
    },
    "orientation" : 14
  }, {
    "shape" : "d2fbd12e-e9af-404d-8b9f-e73f4cb6be72",
    "color" : "#000000",
    "position" : {
      "x" : -9.110821,
      "y" : -3.7738254,
      "z" : 3.7738254
    },
    "orientation" : 3
  }, {
    "shape" : "205537e0-8581-4ba9-8720-98b31e1a3437",
    "color" : "#000000",
    "position" : {
      "x" : -9.110821,
      "y" : 3.7738254,
      "z" : 3.7738254
    },
    "orientation" : 6
  }, {
    "shape" : "6da46770-8560-4386-93b5-0857fb4977bc",
    "color" : "#FFFFFF",
    "position" : {
      "x" : 0.0,
      "y" : 0.0,
      "z" : 0.0
    }
  }, {
    "shape" : "9418330a-e9b1-4b74-b119-70db2e54bc35",
    "color" : "#0000FF",
    "position" : {
      "x" : 0.0,
      "y" : 0.0,
      "z" : 0.0
    }
  }, {
    "shape" : "d2fbd12e-e9af-404d-8b9f-e73f4cb6be72",
    "color" : "#000000",
    "position" : {
      "x" : -3.7738254,
      "y" : -9.110821,
      "z" : -3.7738254
    },
    "orientation" : 18
  }, {
    "shape" : "8b79418b-5839-4001-8d52-0a279373b998",
    "color" : "#FFFFFF",
    "position" : {
      "x" : 0.0,
      "y" : 0.0,
      "z" : 0.0
    }
  }, {
    "shape" : "f4712e3d-12dc-496e-a379-c20241718910",
    "color" : "#000000",
    "position" : {
      "x" : 3.7738254,
      "y" : 3.7738254,
      "z" : 9.110821
    }
  }, {
    "shape" : "205537e0-8581-4ba9-8720-98b31e1a3437",
    "color" : "#000000",
    "position" : {
      "x" : 3.7738254,
      "y" : -3.7738254,
      "z" : -9.110821
    },
    "orientation" : 5
  }, {
    "shape" : "d2fbd12e-e9af-404d-8b9f-e73f4cb6be72",
    "color" : "#000000",
    "position" : {
      "x" : -9.110821,
      "y" : -3.7738254,
      "z" : -3.7738254
    },
    "orientation" : 3
  }, {
    "shape" : "bf7ff0f0-6070-4a43-a76a-ed960a84a589",
    "color" : "#FFFFFF",
    "position" : {
      "x" : 0.0,
      "y" : 0.0,
      "z" : 0.0
    }
  }, {
    "shape" : "f4712e3d-12dc-496e-a379-c20241718910",
    "color" : "#000000",
    "position" : {
      "x" : 3.7738254,
      "y" : 9.110821,
      "z" : -3.7738254
    }
  }, {
    "shape" : "229a382c-f152-44c2-9d4a-457eeb9c359f",
    "color" : "#0000FF",
    "position" : {
      "x" : 0.0,
      "y" : 0.0,
      "z" : 0.0
    }
  }, {
    "shape" : "205537e0-8581-4ba9-8720-98b31e1a3437",
    "color" : "#000000",
    "position" : {
      "x" : -3.7738254,
      "y" : -3.7738254,
      "z" : -9.110821
    },
    "orientation" : 5
  }, {
    "shape" : "d2fbd12e-e9af-404d-8b9f-e73f4cb6be72",
    "color" : "#000000",
    "position" : {
      "x" : 3.7738254,
      "y" : 9.110821,
      "z" : -3.7738254
    },
    "orientation" : 19
  }, {
    "shape" : "f4712e3d-12dc-496e-a379-c20241718910",
    "color" : "#000000",
    "position" : {
      "x" : -9.110821,
      "y" : 3.7738254,
      "z" : 3.7738254
    }
  }, {
    "shape" : "d2fbd12e-e9af-404d-8b9f-e73f4cb6be72",
    "color" : "#000000",
    "position" : {
      "x" : 3.7738254,
      "y" : -9.110821,
      "z" : -3.7738254
    },
    "orientation" : 18
  }, {
    "shape" : "205537e0-8581-4ba9-8720-98b31e1a3437",
    "color" : "#000000",
    "position" : {
      "x" : 3.7738254,
      "y" : 9.110821,
      "z" : 3.7738254
    },
    "orientation" : 12
  }, {
    "shape" : "205537e0-8581-4ba9-8720-98b31e1a3437",
    "color" : "#000000",
    "position" : {
      "x" : 3.7738254,
      "y" : 9.110821,
      "z" : -3.7738254
    },
    "orientation" : 12
  }, {
    "shape" : "205537e0-8581-4ba9-8720-98b31e1a3437",
    "color" : "#000000",
    "position" : {
      "x" : 9.110821,
      "y" : 3.7738254,
      "z" : -3.7738254
    },
    "orientation" : 7
  }, {
    "shape" : "f4712e3d-12dc-496e-a379-c20241718910",
    "color" : "#000000",
    "position" : {
      "x" : 0.0,
      "y" : 0.0,
      "z" : 0.0
    }
  }, {
    "shape" : "205537e0-8581-4ba9-8720-98b31e1a3437",
    "color" : "#000000",
    "position" : {
      "x" : -9.110821,
      "y" : 3.7738254,
      "z" : 3.7738254
    },
    "orientation" : 7
  }, {
    "shape" : "8cb92359-f916-4136-9ffa-70d9d2bc412d",
    "color" : "#0000FF",
    "position" : {
      "x" : 0.0,
      "y" : 0.0,
      "z" : 0.0
    }
  }, {
    "shape" : "205537e0-8581-4ba9-8720-98b31e1a3437",
    "color" : "#000000",
    "position" : {
      "x" : -9.110821,
      "y" : 3.7738254,
      "z" : -3.7738254
    },
    "orientation" : 7
  }, {
    "shape" : "f4712e3d-12dc-496e-a379-c20241718910",
    "color" : "#000000",
    "position" : {
      "x" : -3.7738254,
      "y" : 9.110821,
      "z" : 3.7738254
    }
  }, {
    "shape" : "d2fbd12e-e9af-404d-8b9f-e73f4cb6be72",
    "color" : "#000000",
    "position" : {
      "x" : 3.7738254,
      "y" : -3.7738254,
      "z" : -9.110821
    },
    "orientation" : 0
  }, {
    "shape" : "d2fbd12e-e9af-404d-8b9f-e73f4cb6be72",
    "color" : "#000000",
    "position" : {
      "x" : 9.110821,
      "y" : 3.7738254,
      "z" : 3.7738254
    },
    "orientation" : 13
  }, {
    "shape" : "205537e0-8581-4ba9-8720-98b31e1a3437",
    "color" : "#000000",
    "position" : {
      "x" : 3.7738254,
      "y" : -9.110821,
      "z" : 3.7738254
    },
    "orientation" : 6
  }, {
    "shape" : "2cdc8995-46fa-4209-add9-63df74495d35",
    "color" : "#FFFFFF",
    "position" : {
      "x" : 0.0,
      "y" : 0.0,
      "z" : 0.0
    }
  }, {
    "shape" : "572f9828-b639-4e7f-bf40-b08882ab212a",
    "color" : "#FFFFFF",
    "position" : {
      "x" : 0.0,
      "y" : 0.0,
      "z" : 0.0
    }
  }, {
    "shape" : "d2fbd12e-e9af-404d-8b9f-e73f4cb6be72",
    "color" : "#000000",
    "position" : {
      "x" : -9.110821,
      "y" : 3.7738254,
      "z" : -3.7738254
    },
    "orientation" : 1
  }, {
    "shape" : "9c939a3a-4855-49cb-9351-dbff5f00c3fd",
    "color" : "#FFFFFF",
    "position" : {
      "x" : 0.0,
      "y" : 0.0,
      "z" : 0.0
    }
  }, {
    "shape" : "d2fbd12e-e9af-404d-8b9f-e73f4cb6be72",
    "color" : "#000000",
    "position" : {
      "x" : 3.7738254,
      "y" : -3.7738254,
      "z" : 9.110821
    },
    "orientation" : 2
  }, {
    "shape" : "d2fbd12e-e9af-404d-8b9f-e73f4cb6be72",
    "color" : "#000000",
    "position" : {
      "x" : 3.7738254,
      "y" : 3.7738254,
      "z" : 9.110821
    },
    "orientation" : 2
  }, {
    "shape" : "d2fbd12e-e9af-404d-8b9f-e73f4cb6be72",
    "color" : "#000000",
    "position" : {
      "x" : -3.7738254,
      "y" : 9.110821,
      "z" : -3.7738254
    },
    "orientation" : 19
  }, {
    "shape" : "683a5a6e-6f98-4664-b0ac-026f7e123186",
    "color" : "#FFFFFF",
    "position" : {
      "x" : 0.0,
      "y" : 0.0,
      "z" : 0.0
    }
  }, {
    "shape" : "b1594420-ad93-4673-934e-bfad2cac7f8d",
    "color" : "#FFFFFF",
    "position" : {
      "x" : 0.0,
      "y" : 0.0,
      "z" : 0.0
    }
  }, {
    "shape" : "205537e0-8581-4ba9-8720-98b31e1a3437",
    "color" : "#000000",
    "position" : {
      "x" : 9.110821,
      "y" : -3.7738254,
      "z" : -3.7738254
    },
    "orientation" : 4
  }, {
    "shape" : "205537e0-8581-4ba9-8720-98b31e1a3437",
    "color" : "#000000",
    "position" : {
      "x" : 3.7738254,
      "y" : -3.7738254,
      "z" : 9.110821
    },
    "orientation" : 12
  }, {
    "shape" : "d2fbd12e-e9af-404d-8b9f-e73f4cb6be72",
    "color" : "#000000",
    "position" : {
      "x" : -9.110821,
      "y" : 3.7738254,
      "z" : 3.7738254
    },
    "orientation" : 0
  }, {
    "shape" : "f4712e3d-12dc-496e-a379-c20241718910",
    "color" : "#000000",
    "position" : {
      "x" : -3.7738254,
      "y" : -9.110821,
      "z" : -3.7738254
    }
  }, {
    "shape" : "f4712e3d-12dc-496e-a379-c20241718910",
    "color" : "#000000",
    "position" : {
      "x" : 3.7738254,
      "y" : -9.110821,
      "z" : -3.7738254
    }
  }, {
    "shape" : "205537e0-8581-4ba9-8720-98b31e1a3437",
    "color" : "#000000",
    "position" : {
      "x" : 3.7738254,
      "y" : 9.110821,
      "z" : -3.7738254
    },
    "orientation" : 4
  }, {
    "shape" : "d2fbd12e-e9af-404d-8b9f-e73f4cb6be72",
    "color" : "#000000",
    "position" : {
      "x" : 9.110821,
      "y" : 3.7738254,
      "z" : -3.7738254
    },
    "orientation" : 13
  }, {
    "shape" : "f4712e3d-12dc-496e-a379-c20241718910",
    "color" : "#000000",
    "position" : {
      "x" : -3.7738254,
      "y" : -3.7738254,
      "z" : -9.110821
    }
  }, {
    "shape" : "dce7d9c2-016f-4be0-b60c-22aa2b370c85",
    "color" : "#0000FF",
    "position" : {
      "x" : 0.0,
      "y" : 0.0,
      "z" : 0.0
    }
  }, {
    "shape" : "6084b1d5-613c-4800-9f40-f45dbb535e01",
    "color" : "#FFFFFF",
    "position" : {
      "x" : 0.0,
      "y" : 0.0,
      "z" : 0.0
    }
  }, {
    "shape" : "205537e0-8581-4ba9-8720-98b31e1a3437",
    "color" : "#000000",
    "position" : {
      "x" : -3.7738254,
      "y" : -9.110821,
      "z" : -3.7738254
    },
    "orientation" : 4
  }, {
    "shape" : "d5bb01bd-8a83-44d9-8994-15159489fcd6",
    "color" : "#0000FF",
    "position" : {
      "x" : 0.0,
      "y" : 0.0,
      "z" : 0.0
    }
  }, {
    "shape" : "d2fbd12e-e9af-404d-8b9f-e73f4cb6be72",
    "color" : "#000000",
    "position" : {
      "x" : 3.7738254,
      "y" : 3.7738254,
      "z" : -9.110821
    },
    "orientation" : 0
  }, {
    "shape" : "833c05aa-cb0e-4b58-a49e-612b9cb22153",
    "color" : "#FFFFFF",
    "position" : {
      "x" : 0.0,
      "y" : 0.0,
      "z" : 0.0
    }
  }, {
    "shape" : "985dd9d6-9c4b-4e32-94f2-259c34228aab",
    "color" : "#FFFFFF",
    "position" : {
      "x" : 0.0,
      "y" : 0.0,
      "z" : 0.0
    }
  }, {
    "shape" : "205537e0-8581-4ba9-8720-98b31e1a3437",
    "color" : "#000000",
    "position" : {
      "x" : -9.110821,
      "y" : -3.7738254,
      "z" : -3.7738254
    },
    "orientation" : 4
  }, {
    "shape" : "5bd03eeb-c3ff-49fa-ab0f-2d7a2304d3fd",
    "color" : "#FFFFFF",
    "position" : {
      "x" : 0.0,
      "y" : 0.0,
      "z" : 0.0
    }
  }, {
    "shape" : "f4712e3d-12dc-496e-a379-c20241718910",
    "color" : "#000000",
    "position" : {
      "x" : 9.110821,
      "y" : -3.7738254,
      "z" : 3.7738254
    }
  }, {
    "shape" : "d2fbd12e-e9af-404d-8b9f-e73f4cb6be72",
    "color" : "#000000",
    "position" : {
      "x" : -3.7738254,
      "y" : 3.7738254,
      "z" : 9.110821
    },
    "orientation" : 18
  }, {
    "shape" : "f4712e3d-12dc-496e-a379-c20241718910",
    "color" : "#000000",
    "position" : {
      "x" : 9.110821,
      "y" : 3.7738254,
      "z" : 3.7738254
    }
  }, {
    "shape" : "f4712e3d-12dc-496e-a379-c20241718910",
    "color" : "#000000",
    "position" : {
      "x" : -9.110821,
      "y" : -3.7738254,
      "z" : -3.7738254
    }
  }, {
    "shape" : "205537e0-8581-4ba9-8720-98b31e1a3437",
    "color" : "#000000",
    "position" : {
      "x" : 9.110821,
      "y" : -3.7738254,
      "z" : 3.7738254
    },
    "orientation" : 5
  }, {
    "shape" : "7a58878c-e75c-4c99-b48a-556928cc13db",
    "color" : "#FFFFFF",
    "position" : {
      "x" : 0.0,
      "y" : 0.0,
      "z" : 0.0
    }
  }, {
    "shape" : "68352985-3a73-43cd-b686-f3598374c5e9",
    "color" : "#FFFFFF",
    "position" : {
      "x" : 0.0,
      "y" : 0.0,
      "z" : 0.0
    }
  }, {
    "shape" : "d2fbd12e-e9af-404d-8b9f-e73f4cb6be72",
    "color" : "#000000",
    "position" : {
      "x" : -3.7738254,
      "y" : -3.7738254,
      "z" : 9.110821
    },
    "orientation" : 19
  }, {
    "shape" : "205537e0-8581-4ba9-8720-98b31e1a3437",
    "color" : "#000000",
    "position" : {
      "x" : -3.7738254,
      "y" : 9.110821,
      "z" : 3.7738254
    },
    "orientation" : 6
  } ],
  "scenes" : [ ],
  "snapshots" : [ ]
}